hurstexponent/__init__.py
hurstexponent/hurst_exponent.py
hurstexponent-0.1.1.dist-info/LICENSE
hurstexponent-0.1.1.dist-info/METADATA
hurstexponent-0.1.1.dist-info/WHEEL
hurstexponent-0.1.1.dist-info/top_level.txt
hurstexponent-0.1.1.dist-info/RECORD
