Metadata-Version: 2.1
Name: hurstexponent
Version: 0.1.1
Summary: Hurst exponent estimator
Home-page: https://github.com/anabugaenko/hurstexponent
Author: Anastasia Bugeenko
Author-email: anabugaenko@gmail.com
License: MIT
Keywords: hurst autocorrelation time-series fractals
Classifier: Programming Language :: Python :: 3
Classifier: License :: OSI Approved :: MIT License
Classifier: Operating System :: OS Independent
Classifier: Topic :: Scientific/Engineering :: Mathematics
Classifier: Intended Audience :: Science/Research
License-File: LICENSE
Requires-Dist: scipy
Requires-Dist: numpy
Requires-Dist: pandas
Requires-Dist: typing
Requires-Dist: statsmodels
Requires-Dist: hurst
Requires-Dist: matplotlib
